README.md
setup.py
colabo/__init__.py
colabo.flow.audit.egg-info/PKG-INFO
colabo.flow.audit.egg-info/SOURCES.txt
colabo.flow.audit.egg-info/dependency_links.txt
colabo.flow.audit.egg-info/requires.txt
colabo.flow.audit.egg-info/top_level.txt
colabo/flow/__init__.py
colabo/flow/audit/__init__.py
colabo/flow/audit/audit_pb2.py
colabo/flow/audit/audit_pb2_grpc.py
colabo/flow/audit/colaboflow_audit_client.py